chetan/__init__.py
chetan/agent/Agent.py
chetan/agent/AgentBody.py
chetan/agent/AgentCore.py
chetan/agent/AgentExecutor.py
chetan/agent/AgentResponse.py
chetan/core/Context.py
chetan/core/Decision.py
chetan/core/Prompt.py
chetan/knowledge/Knowledgebase.py
chetan/llms/groq.py
chetan/llms/llm.py
chetan/llms/ollama.py
chetan/llms/openai.py
chetan/recipe/MitraAgentBody.py
chetan/recipe/MitraAgentCore.py
chetan/recipe/task/Task.py
chetan/recipe/task/TaskDecompose.py
chetan/util/InputParser.py
chetan-0.0.1.dist-info/METADATA
chetan-0.0.1.dist-info/WHEEL
chetan-0.0.1.dist-info/RECORD
